typhoon_asr/__init__.py
typhoon_asr/cli.py
typhoon_asr-0.1.0.dist-info/METADATA
typhoon_asr-0.1.0.dist-info/WHEEL
typhoon_asr-0.1.0.dist-info/entry_points.txt
typhoon_asr-0.1.0.dist-info/top_level.txt
typhoon_asr-0.1.0.dist-info/RECORD
