Metadata-Version: 2.4
Name: typhoon-asr
Version: 0.1.0
Summary: A user-friendly package for Thai speech recognition using the Typhoon ASR model.
Author-email: Warit Sirichotedumrong <warit@scb10x.com>
Project-URL: Homepage, https://github.com/scb10x/typhoon-asr
Project-URL: Bug Tracker, https://github.com/scb10x/typhoon-asr/issues
Classifier: Programming Language :: Python :: 3
Classifier: License :: OSI Approved :: Apache Software License
Classifier: Operating System :: OS Independent
Requires-Python: >=3.8
Requires-Dist: nemo-toolkit[asr]>=1.21.0
Requires-Dist: torch
Requires-Dist: librosa
Requires-Dist: soundfile
